MonEater-0.1.0.data/scripts/fileeater.py
MonEater-0.1.0.data/scripts/moneater.py
eaters/CO2200.py
eaters/__init__.py
eaters/tabeater.py
MonEater-0.1.0.dist-info/METADATA
MonEater-0.1.0.dist-info/WHEEL
MonEater-0.1.0.dist-info/top_level.txt
MonEater-0.1.0.dist-info/RECORD
