Metadata-Version: 2.1
Name: MonEater
Version: 0.1.0
Summary: Monitor, transform and upload program output to InfluxDB.
Home-page: https://gitlab.cern.ch/berkeleylab/moneater
Author: Karol Krizka
Author-email: kkrizka@gmail.com
License: UNKNOWN
Platform: UNKNOWN
Requires-Dist: influxdb
Requires-Dist: pyyaml
